claude_hooks/__init__.py
claude_hooks/cli.py
claude_hooks/hook_utils.py
claude_hooks-0.1.0.dist-info/METADATA
claude_hooks-0.1.0.dist-info/WHEEL
claude_hooks-0.1.0.dist-info/entry_points.txt
claude_hooks-0.1.0.dist-info/licenses/LICENSE
claude_hooks-0.1.0.dist-info/RECORD
