Metadata-Version: 2.4
Name: claude-hooks
Version: 0.1.0
Summary: Python utilities for handling Claude Code hooks with a framework for creating event-driven hooks
Project-URL: Homepage, https://github.com/chrissanders/claude-hooks
Project-URL: Repository, https://github.com/chrissanders/claude-hooks
Project-URL: Issues, https://github.com/chrissanders/claude-hooks/issues
Author-email: Chris Sanders <sanders.chris@gmail.com>
License: Apache-2.0
License-File: LICENSE
Keywords: ai,automation,claude,hooks
Classifier: Development Status :: 3 - Alpha
Classifier: Intended Audience :: Developers
Classifier: License :: OSI Approved :: Apache Software License
Classifier: Programming Language :: Python :: 3
Classifier: Programming Language :: Python :: 3.12
Classifier: Programming Language :: Python :: 3.13
Classifier: Topic :: Software Development :: Libraries :: Python Modules
Classifier: Topic :: Utilities
Requires-Python: >=3.12
Requires-Dist: click>=8.0.0
Provides-Extra: dev
Requires-Dist: pytest>=7.0.0; extra == 'dev'
Requires-Dist: ruff>=0.12.0; extra == 'dev'
